onepyece/__init__.py
onepyece/api.py
onepyece/common.py
onepyece/functions.py
onepyece/interface.py
onepyece-2.0.1.dist-info/LICENSE
onepyece-2.0.1.dist-info/METADATA
onepyece-2.0.1.dist-info/WHEEL
onepyece-2.0.1.dist-info/top_level.txt
onepyece-2.0.1.dist-info/RECORD
