Metadata-Version: 2.1
Name: onepyece
Version: 2.0.1
Summary: A package to use the One-Piece API : https://api-onepiece.com/
Home-page: https://github.com/icepick4/onepyece
Author: Rémi JARA
Author-email: remi.jara4@gmail.com
License: MIT
Keywords: one-piece api wrapper onepyece onepiece onepiece-api onepiece-api-wrapper manga anime anime-manga
Classifier: Programming Language :: Python :: 3.8
Classifier: Programming Language :: Python :: 3.9
Classifier: Programming Language :: Python :: 3.10
Classifier: License :: OSI Approved :: MIT License
Classifier: Operating System :: OS Independent
Requires-Python: >=3.8
License-File: LICENSE
Requires-Dist: requests
